{"file:///Users/sharon/sharon-mft":{"assets/images/hashes.json":"CN0fgQ/4s4/8pH/IrQwr7w==","assets/images/screen-shot-2020-05-23-at-10.17.36-1920x1274.jpg":"3yAPZ/DwPNpUT+75Aft2HA==","assets/images/trend13.jpg":"mKvGLK6RAVAcLApYZJix3w==","assets/images/quadr.svg":"xCbw/txjNbvv14IeWZe5vA==","assets/images/mbr-1-946x631.jpg":"48uMco7quH1mLpJ4eeThOw==","assets/images/mbr-946x605.jpg":"VwfbIszImD5T/UGdLdsHvw==","assets/images/mbr-946x1425.jpg":"X9EOYVx3M23PCfEU4bu+wA==","assets/images/mbr-3-180x180.png":"J3oBjefuQM1Q9KCI+G270w==","assets/images/mbr-2-180x180.png":"JQlYUvB6T+uTeCLPQKt1pg==","assets/images/mbr-180x223.png":"tR7YFtoA29Xcte3qqSAM/Q==","assets/images/mbr-180x162.png":"B4+lFbHXZnbyfKxguvPV7A==","assets/images/mbr-1-180x180.png":"4LB/UaWJqT26u/eSXmG93A==","assets/images/mbr-180x180.png":"F3pXoyPqGJR/oKSJxfUtbQ==","assets/images/animation-fon.png":"5UA0V+ib0DxEK1n5ZP9NGQ==","assets/images/mbr-1-120x120.png":"kbzxsO4TcwSWuldI7W0X4g==","assets/images/mbr-120x120.png":"aEAmB9bHIl6gePKiu4IKdQ==","assets/images/transparent-fon.png":"g3UIaKSAvwo3fwU/p8ANmw==","assets/images/triangle-green-transp.svg":"V6iGTa54u4eg691AJpNQzA==","assets/images/logo-school-140x140.png":"DemEOBMaiYKyZ0Y/uCaVNA==","assets/images/mbr-3-1920x1280.jpg":"aYz3SO0ZdcFeXq5zZ8nOGw==","assets/web/assets/jquery/jquery.min.js":"3F5/GMjTasHT1HU6h8mNCg==","assets/bootstrap/css/bootstrap.min.css":"Ov4V6XZzTZ2qwmMQEQxFlA==","assets/bootstrap/css/bootstrap-grid.min.css":"B/UEMwCpd8W0hrWHLpycag==","assets/bootstrap/css/bootstrap-reboot.min.css":"Ui5OyWvr8teeN3hgkVQeIQ==","assets/bootstrap/js/bootstrap.min.js":"a+pgw0xdtnlxUGENrNxrzg==","assets/popper/popper.min.js":"NiE4ESlZe/NNSKniYj4FyQ==","assets/tether/tether.min.css":"YhVaOUjL8Xsb9LQHyQq4Tw==","assets/tether/tether.min.js":"PlC291/0Eo8keLHUT4D9+w==","assets/theme/css/style.css":"jKWQKcNlIvnI9sVTBA/0OA==-VITbTf54ezV7Z7I/e4lZVw==","assets/smoothscroll/smooth-scroll.js":"1fU5SR6w/dKRUCNIywK1Sw==","assets/dropdown/css/style.css":"s+S8lVC62P0BWFtgHpaNFA==","assets/dropdown/js/nav-dropdown.js":"dC/upwyur9A4kPhFrRHwaQ==","assets/dropdown/js/navbar-dropdown.js":"ZePnAsEAv4Y5wJTD95L44g==","assets/touchswipe/jquery.touch-swipe.min.js":"9g/wVGnRdXmW2F9BctT/TQ==","assets/animatecss/animate.min.css":"F4tlGVjO/1VsvF81Xgi78Q==","assets/viewportchecker/jquery.viewportchecker.js":"tPohzxkhSfLWJO1IZnbd/g==","assets/bootstrapcarouselswipe/bootstrap-carousel-swipe.js":"1NIoKK0GehKy3z7Pjjpsjw==","assets/mbr-testimonials-slider/mbr-testimonials-slider.js":"NKLXlLIaoEW7ybz/7aYRGg==","assets/web/assets/mobirise-icons2/mobirise2.css":"+RO7OxVtE1FsD/N7V3/ADw==","assets/web/assets/mobirise-icons2/mobirise2.eot":"B2EjryGRojlTpzr1GHt3LQ==","assets/web/assets/mobirise-icons2/mobirise2.svg":"usCYAy7QdzckfeGReb9wWQ==","assets/web/assets/mobirise-icons2/mobirise2.ttf":"VMdAr7YYQ2ab9KiUyabAGA==","assets/web/assets/mobirise-icons2/mobirise2.woff":"xY3InaTfYGp0nlCuQBMudQ==","assets/web/assets/mobirise-icons/mobirise-icons.css":"t/IrTIzfJvbDUoCV05F+7Q==","assets/web/assets/mobirise-icons/mobirise-icons.eot":"T9iJ+Vffe7n6Gk/+pf9gEw==","assets/web/assets/mobirise-icons/mobirise-icons.svg":"Yp5pSlGdnLgPdQLUa/Yv3w==","assets/web/assets/mobirise-icons/mobirise-icons.ttf":"r0OtN8kuMaYwUc+mlGDUWA==","assets/web/assets/mobirise-icons/mobirise-icons.woff":"3aYYVAIqADvsB1jjxJZ73w==","assets/web/assets/mobirise-icons-bold/mobirise-icons-bold.css":"oCz4VsqVNHRevrgedUE3iA==","assets/web/assets/mobirise-icons-bold/mobirise-icons-bold.eot":"xL5gaCBkZEP9ksoDCgYMlg==","assets/web/assets/mobirise-icons-bold/mobirise-icons-bold.svg":"/6YZxrduGdMApfjQkLfW0g==","assets/web/assets/mobirise-icons-bold/mobirise-icons-bold.ttf":"My4xH5UmdimFH1eritsxVw==","assets/web/assets/mobirise-icons-bold/mobirise-icons-bold.woff":"4H/XculakPzhz3skasBxzg==","assets/socicon/css/styles.css":"q91aZJ04O5rzI1nJO9PRHw==","assets/socicon/fonts/socicon.eot":"MvYQV8XxgngrhGqjN3oHBw==","assets/socicon/fonts/socicon.svg":"U1iRKoyNjKeR+mUJr3QbXg==","assets/socicon/fonts/socicon.ttf":"IyAo3XNB2a/Q0ml3ZraPsQ==","assets/socicon/fonts/socicon.woff":"zQDjXd6bBUQi87pRsBWVqQ==","assets/socicon/fonts/socicon.woff2":"o3w8h99EHOwP99NXAoHpOQ=="}}